{
    "Name": "优菈",
    "Designation": "浪沫的旋舞",
    "Fullname": "优菈·劳伦斯（Eula Lawrence）",
    "Birthday": "10月25日",
    "Weapon": "双手剑",
    "Country": "",
    "Description": "古老家族出身的「浪花骑士」，西风骑士团游击小队队长。身为旧贵族后裔却加入了堪称死对头的西风骑士团，该事件至今仍是蒙德一大谜团。",
    "Gender": "女",
    "Race": "人类",
    "Star": "5",
    "Vision": "冰",
    "Type": "限定UP",
    "Constellation": "浪沫座",
    "ActualInstallationTime": "2021年05月18日（1.5版本）",
    "Job": "西风骑士团「游击小队」队长",
    "Nicknames": [
        "浪花骑士",
        "「游击小队」队长",
        "绝版角色",
        "喷嚏记仇真君"
    ],
    "TAG": [
        "减抗",
        "炼金返还",
        "自身伤害提升",
        "自身抗打断",
        "物理输出",
        "自身加防",
        "冷却减少"
    ],
    "Photos": {
        "1": "https:\/\/patchwiki.biligame.com\/images\/ys\/f\/f8\/3nzfj3fub35l79p1l58umkpxs5xbg8v.png",
        "2": "https:\/\/patchwiki.biligame.com\/images\/ys\/b\/b7\/r25wv7ybadf9iuiqsgw7uxr9iysnzvu.png",
        "wish": "https:\/\/patchwiki.biligame.com\/images\/ys\/5\/50\/ej8v3104cmwt4lk4iciq4u5fab2h0se.png"
    },
    "CV": {
        "Chinese": "子音",
        "Japanese": "佐藤利奈",
        "Korean": "金炫志",
        "English": "素汐·杨"
    },
    "Stories": {
        "Pron": "优菈在西风骑士团担任「游击小队」队长一职。",
        "1": "既是罪人劳伦斯家后裔、旧贵族的遗毒，也是蒙德数一数二的剑术高手。罪恶的血脉与高超的武艺共同构成了优菈这一个体。",
        "2": "事实上，优菈完全没有危险人物该有的样子。被成见包围的她，有时反而像是的一弱势的一方。",
        "3": "不过，蒙德毕竟是自由快乐之城。即使是罪人的后裔也会交到好朋友。",
        "4": "有别于平日那份疏远与锐利，优菈在厨艺方面颇有心得，能做一手好菜。",
        "5": "传统礼仪之外，艺术是旧贵族最为重视的「第二灵魂」。",
        "Things": "优菈掌管着劳伦斯的家徽「坚冰之印」。它是家族武力的至高象征，代表着蒙德开垦初期劳伦斯一族尚未堕落的意志:冷冽高洁不惧怒焰、坚韧沉着不被撼动。",
        "Vision": "优菈掌管着劳伦斯的家徽「坚冰之印」。它是家族武力的至高象征，代表着蒙德开垦初期劳伦斯一族尚未堕落的意志:冷冽高洁不惧怒焰、坚韧沉着不被撼动。"
    }
}